Metadata-Version: 2.1
Name: Framework-BNE
Version: 1.0.1
Summary: O Framework tem como objetivo auxiliar os brasileiros que estão a procura de emprego a localizarem de maneira mais prática e concisa vagas que lhe interessem, além de apresentar as vagas com candidaturas livres disponíveis no site do BNE(Banco Nacional de Emprego)
Home-page: https://github.com/edufurlani/BNE/tree/main
Author: Beatriz Rodovalho, Eduardo Furlani, Gabriel Benga, Lucas Gregório, Thiago Melo
Author-email: dudufurlani58@gmail.com
License: MIT
Keywords: BNE
Platform: UNKNOWN
License-File: LICENSE.txt
